pmxlock/__init__.py
pmxlock/__main__.py
pmxlock/cli.py
pmxlock/gc.py
pmxlock-1.1.0.dist-info/METADATA
pmxlock-1.1.0.dist-info/WHEEL
pmxlock-1.1.0.dist-info/entry_points.txt
pmxlock-1.1.0.dist-info/licenses/LICENSE
pmxlock-1.1.0.dist-info/RECORD
