Metadata-Version: 2.1
Name: pmxlock
Version: 1.1.0
Summary: Cluster-wide Proxmox pmxcfs locks
Project-URL: Homepage, https://github.com/VadimZud/pmxlock
Project-URL: Bug Tracker, https://github.com/VadimZud/pmxlock/issues
Author-email: Vadim Zudin <zudinvadim@gmail.com>
License-File: LICENSE
Classifier: License :: OSI Approved :: GNU General Public License v3 (GPLv3)
Classifier: Operating System :: POSIX
Classifier: Programming Language :: Python :: 3
Requires-Python: >=3.9
